MANIFEST.in
README.rst
setup.py
open_singly/__init__.py
open_singly/api.py
open_singly.egg-info/PKG-INFO
open_singly.egg-info/SOURCES.txt
open_singly.egg-info/dependency_links.txt
open_singly.egg-info/requires.txt
open_singly.egg-info/top_level.txt
open_singly.egg-info/zip-safe