Metadata-Version: 1.1
Name: open-singly
Version: 0.2
Summary: Implementation of singly API for Python
Home-page: https://github.com/MagicSolutions/open-singly
Author: Venelin Stoykov
Author-email: venelin@magicsolutions.bg
License: UNKNOWN
Platform: UNKNOWN
Classifier: Development Status :: 4 - Beta
Classifier: Environment :: Web Environment
Classifier: Intended Audience :: Developers
Classifier: Operating System :: OS Independent
Classifier: Programming Language :: Python
